{
  "Năm 2021": {
    "Doanh thu thuần": "329,878",
    "Lợi nhuận gộp": "22,227",
    "LN thuần từ HĐKD": "8,490",
    "LNST thu nhập DN": "6,764",
    "LNST của CĐ cty mẹ": "6,764",
    "Tài sản ngắn hạn": "77,039",
    "Tổng tài sản": "93,310",
    "Nợ phải trả": "47,084",
    "Nợ ngắn hạn": "46,967",
    "Vốn chủ sở hữu": "46,227",
    "EPS 4 quý": "2,255.00",
    "BVPS cơ bản": "15,382.00",
    "P/E cơ bản": "8.21",
    "ROS": "2.05",
    "ROEA": "14.80",
    "ROAA": "7.60"
  },
  "Năm 2022": {
    "Doanh thu thuần": "408,472",
    "Lợi nhuận gộp": "31,703",
    "LN thuần từ HĐKD": "9,767",
    "LNST thu nhập DN": "7,770",
    "LNST của CĐ cty mẹ": "7,770",
    "Tài sản ngắn hạn": "102,748",
    "Tổng tài sản": "119,368",
    "Nợ phải trả": "69,986",
    "Nợ ngắn hạn": "69,869",
    "Vốn chủ sở hữu": "49,382",
    "EPS 4 quý": "2,590.00",
    "BVPS cơ bản": "16,434.00",
    "P/E cơ bản": "6.18",
    "ROS": "1.90",
    "ROEA": "16.25",
    "ROAA": "7.31"
  },
  "Năm 2023": {
    "Doanh thu thuần": "322,872",
    "Lợi nhuận gộp": "27,274",
    "LN thuần từ HĐKD": "10,282",
    "LNST thu nhập DN": "8,290",
    "LNST của CĐ cty mẹ": "8,290",
    "Tài sản ngắn hạn": "81,679",
    "Tổng tài sản": "95,665",
    "Nợ phải trả": "42,952",
    "Nợ ngắn hạn": "42,836",
    "Vốn chủ sở hữu": "52,713",
    "EPS 4 quý": "2,763.00",
    "BVPS cơ bản": "17,544.00",
    "P/E cơ bản": "8.21",
    "ROS": "2.57",
    "ROEA": "16.24",
    "ROAA": "7.71"
  },
  "Năm 2024": {
    "Doanh thu thuần": "441,545",
    "Lợi nhuận gộp": "27,611",
    "LN thuần từ HĐKD": "11,034",
    "LNST thu nhập DN": "8,885",
    "LNST của CĐ cty mẹ": "8,885",
    "Tài sản ngắn hạn": "106,739",
    "Tổng tài sản": "118,932",
    "Nợ phải trả": "62,236",
    "Nợ ngắn hạn": "62,111",
    "Vốn chủ sở hữu": "56,697",
    "EPS 4 quý": "2,974.00",
    "BVPS cơ bản": "18,872.00",
    "P/E cơ bản": "6.92",
    "ROS": "2.01",
    "ROEA": "16.24",
    "ROAA": "8.28"
  },
  "Năm 2017": {
    "Doanh thu thuần": "161,946",
    "Lợi nhuận gộp": "19,186",
    "LN thuần từ HĐKD": "5,175",
    "LNST thu nhập DN": "4,283",
    "LNST của CĐ cty mẹ": "4,283",
    "Tài sản ngắn hạn": "50,545",
    "Tổng tài sản": "67,607",
    "Nợ phải trả": "36,631",
    "Nợ ngắn hạn": "36,359",
    "Vốn chủ sở hữu": "30,976",
    "EPS 4 quý": "2,157.00",
    "BVPS cơ bản": "15,562.00",
    "P/E cơ bản": "3.62",
    "ROS": "2.64",
    "ROEA": "14.05",
    "ROAA": "6.22"
  },
  "Năm 2018": {
    "Doanh thu thuần": "253,240",
    "Lợi nhuận gộp": "20,932",
    "LN thuần từ HĐKD": "5,983",
    "LNST thu nhập DN": "5,045",
    "LNST của CĐ cty mẹ": "5,045",
    "Tài sản ngắn hạn": "75,473",
    "Tổng tài sản": "91,735",
    "Nợ phải trả": "49,235",
    "Nợ ngắn hạn": "48,972",
    "Vốn chủ sở hữu": "42,500",
    "EPS 4 quý": "2,541.00",
    "BVPS cơ bản": "21,366.00",
    "P/E cơ bản": "4.76",
    "ROS": "1.99",
    "ROEA": "13.73",
    "ROAA": "6.33"
  },
  "Năm 2019": {
    "Doanh thu thuần": "279,311",
    "Lợi nhuận gộp": "20,885",
    "LN thuần từ HĐKD": "6,938",
    "LNST thu nhập DN": "5,795",
    "LNST của CĐ cty mẹ": "5,795",
    "Tài sản ngắn hạn": "69,372",
    "Tổng tài sản": "88,832",
    "Nợ phải trả": "44,921",
    "Nợ ngắn hạn": "44,748",
    "Vốn chủ sở hữu": "43,911",
    "EPS 4 quý": "2,919.00",
    "BVPS cơ bản": "22,076.00",
    "P/E cơ bản": "5.48",
    "ROS": "2.07",
    "ROEA": "13.41",
    "ROAA": "6.42"
  },
  "Năm 2020": {
    "Doanh thu thuần": "328,775",
    "Lợi nhuận gộp": "21,134",
    "LN thuần từ HĐKD": "7,442",
    "LNST thu nhập DN": "6,379",
    "LNST của CĐ cty mẹ": "6,379",
    "Tài sản ngắn hạn": "67,169",
    "Tổng tài sản": "84,632",
    "Nợ phải trả": "39,456",
    "Nợ ngắn hạn": "39,338",
    "Vốn chủ sở hữu": "45,176",
    "EPS 4 quý": "2,479.00",
    "BVPS cơ bản": "15,032.00",
    "P/E cơ bản": "6.78",
    "ROS": "1.94",
    "ROEA": "14.32",
    "ROAA": "7.35"
  },
  "Năm 2013": {
    "Doanh thu thuần": "117,471",
    "Lợi nhuận gộp": "21,196",
    "LN thuần từ HĐKD": "4,259",
    "LNST thu nhập DN": "3,513",
    "LNST của CĐ cty mẹ": "3,513",
    "Tài sản ngắn hạn": "60,090",
    "Tổng tài sản": "81,190",
    "Nợ phải trả": "52,871",
    "Nợ ngắn hạn": "52,088",
    "Vốn chủ sở hữu": "28,320",
    "EPS 4 quý": "1,769.00",
    "BVPS cơ bản": "14,224.00",
    "P/E cơ bản": "4.58",
    "ROS": "2.99",
    "ROEA": "12.63",
    "ROAA": "4.00"
  },
  "Năm 2014": {
    "Doanh thu thuần": "249,740",
    "Lợi nhuận gộp": "24,012",
    "LN thuần từ HĐKD": "4,335",
    "LNST thu nhập DN": "3,412",
    "LNST của CĐ cty mẹ": "3,412",
    "Tài sản ngắn hạn": "92,112",
    "Tổng tài sản": "112,142",
    "Nợ phải trả": "83,553",
    "Nợ ngắn hạn": "82,817",
    "Vốn chủ sở hữu": "28,589",
    "EPS 4 quý": "1,718.00",
    "BVPS cơ bản": "14,359.00",
    "P/E cơ bản": "7.62",
    "ROS": "1.37",
    "ROEA": "11.99",
    "ROAA": "3.53"
  },
  "Năm 2015": {
    "Doanh thu thuần": "169,150",
    "Lợi nhuận gộp": "19,632",
    "LN thuần từ HĐKD": "4,003",
    "LNST thu nhập DN": "3,478",
    "LNST của CĐ cty mẹ": "3,478",
    "Tài sản ngắn hạn": "55,534",
    "Tổng tài sản": "73,877",
    "Nợ phải trả": "44,362",
    "Nợ ngắn hạn": "42,821",
    "Vốn chủ sở hữu": "29,514",
    "EPS 4 quý": "1,752.00",
    "BVPS cơ bản": "14,825.00",
    "P/E cơ bản": "6.79",
    "ROS": "2.06",
    "ROEA": "11.97",
    "ROAA": "3.74"
  },
  "Năm 2016": {
    "Doanh thu thuần": "146,035",
    "Lợi nhuận gộp": "19,351",
    "LN thuần từ HĐKD": "4,140",
    "LNST thu nhập DN": "3,516",
    "LNST của CĐ cty mẹ": "3,516",
    "Tài sản ngắn hạn": "52,940",
    "Tổng tài sản": "70,218",
    "Nợ phải trả": "40,217",
    "Nợ ngắn hạn": "39,923",
    "Vốn chủ sở hữu": "30,001",
    "EPS 4 quý": "1,771.00",
    "BVPS cơ bản": "15,070.00",
    "P/E cơ bản": "6.21",
    "ROS": "2.41",
    "ROEA": "11.82",
    "ROAA": "4.88"
  },
  "Năm 2009": {
    "Doanh thu thuần": "94,913",
    "Lợi nhuận gộp": "10,690",
    "LN thuần từ HĐKD": "879",
    "LNST thu nhập DN": "844",
    "LNST của CĐ cty mẹ": "844",
    "Tài sản ngắn hạn": "52,315",
    "Tổng tài sản": "77,745",
    "Nợ phải trả": "55,452",
    "Nợ ngắn hạn": "48,264",
    "Vốn chủ sở hữu": "22,292",
    "EPS 4 quý": "425.00",
    "BVPS cơ bản": "11,198.00",
    "P/E cơ bản": "0",
    "ROS": "0.89",
    "ROEA": "3.85",
    "ROAA": "1.08"
  },
  "Năm 2010": {
    "Doanh thu thuần": "100,390",
    "Lợi nhuận gộp": "14,394",
    "LN thuần từ HĐKD": "3,106",
    "LNST thu nhập DN": "2,978",
    "LNST của CĐ cty mẹ": "2,978",
    "Tài sản ngắn hạn": "77,163",
    "Tổng tài sản": "103,956",
    "Nợ phải trả": "79,248",
    "Nợ ngắn hạn": "72,214",
    "Vốn chủ sở hữu": "24,708",
    "EPS 4 quý": "1,500.00",
    "BVPS cơ bản": "12,405.00",
    "P/E cơ bản": "7.33",
    "ROS": "2.97",
    "ROEA": "12.67",
    "ROAA": "3.28"
  },
  "Năm 2011": {
    "Doanh thu thuần": "113,943",
    "Lợi nhuận gộp": "22,520",
    "LN thuần từ HĐKD": "6,350",
    "LNST thu nhập DN": "5,545",
    "LNST của CĐ cty mẹ": "5,545",
    "Tài sản ngắn hạn": "73,705",
    "Tổng tài sản": "99,038",
    "Nợ phải trả": "70,887",
    "Nợ ngắn hạn": "66,904",
    "Vốn chủ sở hữu": "28,151",
    "EPS 4 quý": "2,793.00",
    "BVPS cơ bản": "14,139.00",
    "P/E cơ bản": "1.07",
    "ROS": "4.87",
    "ROEA": "20.98",
    "ROAA": "5.46"
  },
  "Năm 2012": {
    "Doanh thu thuần": "115,971",
    "Lợi nhuận gộp": "21,605",
    "LN thuần từ HĐKD": "3,745",
    "LNST thu nhập DN": "3,007",
    "LNST của CĐ cty mẹ": "3,007",
    "Tài sản ngắn hạn": "72,407",
    "Tổng tài sản": "94,650",
    "Nợ phải trả": "67,339",
    "Nợ ngắn hạn": "65,014",
    "Vốn chủ sở hữu": "27,310",
    "EPS 4 quý": "1,515.00",
    "BVPS cơ bản": "13,715.00",
    "P/E cơ bản": "4.23",
    "ROS": "2.59",
    "ROEA": "10.84",
    "ROAA": "3.11"
  },
  "Năm 2008": {
    "Doanh thu thuần": "86,752",
    "Lợi nhuận gộp": "8,890",
    "LN thuần từ HĐKD": "180",
    "LNST thu nhập DN": "206",
    "LNST của CĐ cty mẹ": "206",
    "Tài sản ngắn hạn": "52,615",
    "Tổng tài sản": "79,028",
    "Nợ phải trả": "57,438",
    "Nợ ngắn hạn": "48,948",
    "Vốn chủ sở hữu": "21,590",
    "EPS 4 quý": "104.00",
    "BVPS cơ bản": "10,844.00",
    "P/E cơ bản": "0",
    "ROS": "0.24",
    "ROEA": "1.90",
    "ROAA": "0.52"
  }
}