{
  "Năm 2021": {
    "Doanh thu thuần": "1,048,920",
    "Lợi nhuận gộp": "122,588",
    "LN thuần từ HĐKD": "52,226",
    "LNST thu nhập DN": "50,141",
    "LNST của CĐ cty mẹ": "50,141",
    "Tài sản ngắn hạn": "707,903",
    "Tổng tài sản": "1,032,943",
    "Nợ phải trả": "592,321",
    "Nợ ngắn hạn": "450,568",
    "Vốn chủ sở hữu": "440,622",
    "EPS 4 quý": "1,857.00",
    "BVPS cơ bản": "16,319.00",
    "P/E cơ bản": "0",
    "ROS": "4.78",
    "ROEA": "15.38",
    "ROAA": "5.41"
  },
  "Năm 2022": {
    "Doanh thu thuần": "1,178,951",
    "Lợi nhuận gộp": "165,189",
    "LN thuần từ HĐKD": "63,388",
    "LNST thu nhập DN": "54,415",
    "LNST của CĐ cty mẹ": "54,415",
    "Tài sản ngắn hạn": "831,975",
    "Tổng tài sản": "1,359,266",
    "Nợ phải trả": "711,035",
    "Nợ ngắn hạn": "654,073",
    "Vốn chủ sở hữu": "648,231",
    "EPS 4 quý": "1,526.00",
    "BVPS cơ bản": "18,183.00",
    "P/E cơ bản": "8.39",
    "ROS": "4.62",
    "ROEA": "9.99",
    "ROAA": "4.55"
  },
  "Năm 2023": {
    "Doanh thu thuần": "1,481,720",
    "Lợi nhuận gộp": "158,240",
    "LN thuần từ HĐKD": "48,993",
    "LNST thu nhập DN": "43,162",
    "LNST của CĐ cty mẹ": "43,162",
    "Tài sản ngắn hạn": "823,097",
    "Tổng tài sản": "1,532,921",
    "Nợ phải trả": "844,248",
    "Nợ ngắn hạn": "799,144",
    "Vốn chủ sở hữu": "688,672",
    "EPS 4 quý": "1,211.00",
    "BVPS cơ bản": "19,318.00",
    "P/E cơ bản": "9.58",
    "ROS": "2.91",
    "ROEA": "6.46",
    "ROAA": "2.98"
  },
  "Năm 2024": {
    "Doanh thu thuần": "1,579,969",
    "Lợi nhuận gộp": "140,598",
    "LN thuần từ HĐKD": "57,816",
    "LNST thu nhập DN": "47,875",
    "LNST của CĐ cty mẹ": "47,875",
    "Tài sản ngắn hạn": "940,865",
    "Tổng tài sản": "1,634,570",
    "Nợ phải trả": "898,023",
    "Nợ ngắn hạn": "869,787",
    "Vốn chủ sở hữu": "736,547",
    "EPS 4 quý": "1,256.00",
    "BVPS cơ bản": "17,217.00",
    "P/E cơ bản": "6.24",
    "ROS": "3.03",
    "ROEA": "6.72",
    "ROAA": "3.02"
  },
  "Năm 2018": {
    "Doanh thu thuần": "454,106",
    "Lợi nhuận gộp": "40,708",
    "LN thuần từ HĐKD": "1,103",
    "LNST thu nhập DN": "97",
    "LNST của CĐ cty mẹ": "97",
    "Tài sản ngắn hạn": "301,955",
    "Tổng tài sản": "447,497",
    "Nợ phải trả": "396,803",
    "Nợ ngắn hạn": "275,217",
    "Vốn chủ sở hữu": "50,694",
    "EPS 4 quý": "19.00",
    "BVPS cơ bản": "10,139.00",
    "ROS": "0.02",
    "ROEA": "0.38",
    "ROAA": "0.04"
  },
  "Năm 2019": {
    "Doanh thu thuần": "724,569",
    "Lợi nhuận gộp": "61,218",
    "LN thuần từ HĐKD": "12,289",
    "LNST thu nhập DN": "9,553",
    "LNST của CĐ cty mẹ": "9,553",
    "Tài sản ngắn hạn": "549,094",
    "Tổng tài sản": "699,844",
    "Nợ phải trả": "599,810",
    "Nợ ngắn hạn": "492,407",
    "Vốn chủ sở hữu": "100,034",
    "EPS 4 quý": "1,061.00",
    "BVPS cơ bản": "11,115.00",
    "ROS": "1.32",
    "ROEA": "12.68",
    "ROAA": "1.67"
  },
  "Năm 2020": {
    "Doanh thu thuần": "842,716",
    "Lợi nhuận gộp": "90,054",
    "LN thuần từ HĐKD": "29,099",
    "LNST thu nhập DN": "24,524",
    "LNST của CĐ cty mẹ": "24,524",
    "Tài sản ngắn hạn": "620,443",
    "Tổng tài sản": "820,855",
    "Nợ phải trả": "609,298",
    "Nợ ngắn hạn": "475,113",
    "Vốn chủ sở hữu": "211,558",
    "EPS 4 quý": "1,635.00",
    "BVPS cơ bản": "14,104.00",
    "ROS": "2.91",
    "ROEA": "15.74",
    "ROAA": "3.23"
  }
}